CHANGES.txt
CONTRIBUTORS.txt
MANIFEST.in
README.rst
bootstrap.py
buildout.cfg
setup.py
./collective/__init__.py
./collective/recipe/__init__.py
./collective/recipe/ropeproject/__init__.py
./collective/recipe/ropeproject/tests/__init__.py
./collective/recipe/ropeproject/tests/test_docs.py
collective.recipe.ropeproject.egg-info/PKG-INFO
collective.recipe.ropeproject.egg-info/SOURCES.txt
collective.recipe.ropeproject.egg-info/dependency_links.txt
collective.recipe.ropeproject.egg-info/entry_points.txt
collective.recipe.ropeproject.egg-info/namespace_packages.txt
collective.recipe.ropeproject.egg-info/not-zip-safe
collective.recipe.ropeproject.egg-info/requires.txt
collective.recipe.ropeproject.egg-info/top_level.txt