Metadata-Version: 1.1
Name: collective.recipe.ropeproject
Version: 1.0b3
Summary: zc.buildout recipe that creates a rope project config with python_path pointing to some eggs and their dependencies
Home-page: http://pypi.python.org/pypi/collective.recipe.ropeproject
Author: Marcio Mazza
Author-email: marciomazza@gmail.com
License: GPL
Keywords: buildout eggs rope refactoring emacs vim
Platform: UNKNOWN
Classifier: Framework :: Buildout
Classifier: Intended Audience :: Developers
Classifier: Topic :: Software Development :: Build Tools
Classifier: Topic :: Software Development :: Libraries :: Python Modules
Classifier: License :: OSI Approved :: GNU General Public License (GPL)
Classifier: Programming Language :: Python :: 2.4
Classifier: Programming Language :: Python :: 2.5
Classifier: Programming Language :: Python :: 2.6
Classifier: Programming Language :: Python :: 2.7
